redstream/__init__.py
redstream/config.py
redstream/consumer_group_manager.py
redstream/handler.py
redstream/redis_cache.py
redstream/request_handler.py
redstream/router.py
redstream/types/__init__.py
redstream/types/rs_message.py
redstream/types/rs_message_status.py
redstream/utils/logging_helpers.py
redstream-0.1.5.dist-info/licenses/LICENSE
redstream-0.1.5.dist-info/METADATA
redstream-0.1.5.dist-info/WHEEL
redstream-0.1.5.dist-info/top_level.txt
redstream-0.1.5.dist-info/RECORD
