Metadata-Version: 2.4
Name: redstream
Version: 0.1.5
Summary: Асинхронный инструментарий для работы с Redis Streams и конфигурациями
Author-email: Albert Toma <cornil@mail.ru>
License: MIT
Project-URL: Homepage, https://github.com/Cornil79/redstream
Keywords: redis,async,streams,configuration
Classifier: Programming Language :: Python :: 3
Classifier: License :: OSI Approved :: MIT License
Classifier: Operating System :: OS Independent
Requires-Python: >=3.8
License-File: LICENSE
Requires-Dist: redis>=5.2.0
Requires-Dist: pytz
Dynamic: license-file
